m3_objectpack-2.4.0.dist-info/licenses/LICENSE
objectpack/__init__.py
objectpack/actions.py
objectpack/column_filters.py
objectpack/desktop.py
objectpack/exceptions.py
objectpack/filters.py
objectpack/models.py
objectpack/tests.py
objectpack/tools.py
objectpack/ui.py
objectpack/version.py
objectpack/dictionary_object_pack/__init__.py
objectpack/dictionary_object_pack/actions.py
objectpack/locale/en/LC_MESSAGES/django.mo
objectpack/locale/en/LC_MESSAGES/django.po
objectpack/observer/__init__.py
objectpack/observer/base.py
objectpack/observer/tools.py
objectpack/slave_object_pack/__init__.py
objectpack/slave_object_pack/actions.py
objectpack/static/css/filter/equals.png
objectpack/static/css/filter/find.png
objectpack/static/css/filter/greater_then.png
objectpack/static/css/filter/hd-btn.gif
objectpack/static/css/filter/header_bg.gif
objectpack/static/css/filter/less_then.png
objectpack/static/css/filter/sort_filtered_asc.gif
objectpack/static/css/filter/sort_filtered_desc.gif
objectpack/static/css/filter/style.css
objectpack/static/js/GridFilters.js
objectpack/static/js/jquery-1.7.2.min.js
objectpack/static/js/filter/BooleanFilter.js
objectpack/static/js/filter/DateFilter.js
objectpack/static/js/filter/Filter.js
objectpack/static/js/filter/ListFilter.js
objectpack/static/js/filter/NumericFilter.js
objectpack/static/js/filter/StringFilter.js
objectpack/static/js/menu/EditableItem.js
objectpack/static/js/menu/ListMenu.js
objectpack/static/js/menu/RangeMenu.js
objectpack/static/js/menu/TreeMenu.js
objectpack/templates/multi-select-window.js
objectpack/templates/select-window.js
objectpack/templates/tabbed-window.js
objectpack/templates/tree-list-window.js
objectpack/templates/tree-select-window.js
objectpack/tree_object_pack/__init__.py
objectpack/tree_object_pack/actions.py
objectpack/tree_object_pack/ui.py
objectpack/tree_object_pack/utils.py
m3_objectpack-2.4.0.dist-info/METADATA
m3_objectpack-2.4.0.dist-info/WHEEL
m3_objectpack-2.4.0.dist-info/dependency_links.txt
m3_objectpack-2.4.0.dist-info/top_level.txt
m3_objectpack-2.4.0.dist-info/RECORD
