Metadata-Version: 2.4
Name: m3-objectpack
Version: 2.4.0
Summary: Инструментарий для упрощения разработки реестров и справочников
Home-page: https://bitbucket.org/barsgroup/objectpack
Author: Alexey Pirogov
Author-email: pirogov@bars-open.ru
License: MIT
Classifier: Intended Audience :: Developers
Classifier: Environment :: Web Environment
Classifier: Natural Language :: Russian
Classifier: Natural Language :: English
Classifier: Operating System :: OS Independent
Classifier: Programming Language :: Python
Classifier: License :: OSI Approved :: MIT License
Classifier: Development Status :: 5 - Production/Stable
Classifier: Programming Language :: Python
Classifier: Programming Language :: Python :: 3.6
Classifier: Programming Language :: Python :: 3.7
Classifier: Framework :: Django :: 1.11
Classifier: Framework :: Django :: 2.0
Classifier: Framework :: Django :: 2.1
Classifier: Framework :: Django :: 2.2
Classifier: Framework :: Django :: 3.0
Classifier: Framework :: Django :: 3.1
Classifier: Framework :: Django :: 3.2
Classifier: Framework :: Django :: 4.0
License-File: LICENSE
Requires-Dist: six<2,>=1.11
Requires-Dist: m3-builder<2,>=1.2
Requires-Dist: m3_django_compatibility<2,>=1.12.0
Requires-Dist: django<5.0,>=1.4
Requires-Dist: m3-core<3,>=2.2.16
Requires-Dist: m3-ui<3,>=2.2.87
Dynamic: author
Dynamic: author-email
Dynamic: classifier
Dynamic: home-page
Dynamic: license
Dynamic: license-file
Dynamic: requires-dist
Dynamic: summary
